.coveragerc
.gitignore
.readthedocs.yml
AUTHORS.md
CHANGELOG.md
Emergence - Steven Johnson.txt
LICENSE.txt
README.md
pyproject.toml
setup.cfg
setup.py
tox.ini
docs/Makefile
docs/authors.md
docs/changelog.md
docs/conf.py
docs/index.md
docs/license.rst
docs/readme.md
docs/requirements.txt
docs/_static/.gitignore
src/psswrd/__init__.py
src/psswrd/psswrd.py
src/psswrd.egg-info/PKG-INFO
src/psswrd.egg-info/SOURCES.txt
src/psswrd.egg-info/dependency_links.txt
src/psswrd.egg-info/entry_points.txt
src/psswrd.egg-info/not-zip-safe
src/psswrd.egg-info/requires.txt
src/psswrd.egg-info/top_level.txt
tests/conftest.py
tests/test_skeleton.py