Metadata-Version: 2.1
Name: psswrd
Version: 0.1.0
Summary: Simple script that generates pronounceable passwords.
Home-page: https://github.com/devbisme/psswrd
Author: Dave Vandenbout
Author-email: devb@xess.com
License: MIT
Platform: Linux
Classifier: Development Status :: 3 - Alpha
Classifier: Programming Language :: Python
Classifier: Intended Audience :: End Users/Desktop
Classifier: License :: OSI Approved :: MIT License
Classifier: Operating System :: POSIX :: Linux
Classifier: Topic :: Utilities
Requires-Python: >=3.8
Provides-Extra: testing
